setup.py
django_revisionfield/__init__.py
django_revisionfield/fields.py
django_revisionfield/models.py
django_revisionfield.egg-info/PKG-INFO
django_revisionfield.egg-info/SOURCES.txt
django_revisionfield.egg-info/dependency_links.txt
django_revisionfield.egg-info/requires.txt
django_revisionfield.egg-info/top_level.txt
tests/__init__.py
tests/app/__init__.py
tests/app/models.py
tests/app/settings.py
tests/app/urls.py