Metadata-Version: 1.0
Name: django-revisionfield
Version: 0.2.2
Summary: An model field that auto increments every time the model is saved
Home-page: https://github.com/bradleyayers/django-revisionfield/
Author: Bradley Ayers
Author-email: bradley.ayers@gmail.com
License: Simplified BSD
Platform: UNKNOWN
Classifier: Environment :: Web Environment
Classifier: Framework :: Django
Classifier: Intended Audience :: Developers
Classifier: Operating System :: OS Independent
Classifier: Programming Language :: Python
Classifier: Topic :: Internet :: WWW/HTTP
Classifier: Topic :: Internet :: WWW/HTTP :: Dynamic Content
Classifier: Topic :: Software Development :: Libraries :: Python Modules
